pybgg_json/__init__.py
pybgg_json/pybgg_cache.py
pybgg_json/pybgg_json.py
pybgg_json/pybgg_utils.py
pybgg_json-0.0.4.dist-info/LICENSE
pybgg_json-0.0.4.dist-info/METADATA
pybgg_json-0.0.4.dist-info/WHEEL
pybgg_json-0.0.4.dist-info/top_level.txt
pybgg_json-0.0.4.dist-info/RECORD
